doc/__init__.py
doc/chapterMaker.py
visca/__init__.py
visca/cameraObject.py
visca/baseClasses/__init__.py
visca/baseClasses/baseInterfaceClass.py
visca/baseClasses/getClass.py
visca/client/__init__.py
visca/client/clientObject.py
visca/dataStucture/__init__.py
visca/dataStucture/commandData.py
visca/dataStucture/commandProcessor.py
visca/dataStucture/messagePacker.py
visca/dataStucture/messageUnpacker.py
visca/dictionary/ViscaDictionary.py
visca/dictionary/__init__.py
visca/dictionary/enumerations.py
visca/interfaces/__init__.py
visca/interfaces/avonicInterface.py
visca/interfaces/colorInterface.py
visca/interfaces/detailIInterface.py
visca/interfaces/exposureInterface.py
visca/interfaces/focusInterface.py
visca/interfaces/gammaInterface.py
visca/interfaces/genericsInterface.py
visca/interfaces/kneeInterface.py
visca/interfaces/panTiltInterface.py
visca/interfaces/presetInterface.py
visca/interfaces/systemInterface.py
visca/interfaces/zoomInterface.py
visca/memories/__init__.py
visca/memories/colorMemories.py
visca/memories/customMemories.py
visca/memories/detailMemories.py
visca/memories/exposureMemories.py
visca/memories/focusMemories.py
visca/memories/gammaMemories.py
visca/memories/genericsMemories.py
visca/memories/kneeMemories.py
visca/memories/panTiltMemories.py
visca/memories/systemMemories.py
visca/memories/zoomMemories.py
viscaSmith-0.4.7.dist-info/LICENSE.md
viscaSmith-0.4.7.dist-info/METADATA
viscaSmith-0.4.7.dist-info/WHEEL
viscaSmith-0.4.7.dist-info/top_level.txt
viscaSmith-0.4.7.dist-info/RECORD
