Metadata-Version: 2.2
Name: viscaSmith
Version: 0.4.7
Summary: Una libreria per controllare telecamere VISCA tramite UDP
Home-page: https://github.com/AlessioMichelassi/ViscaSmithCore
Author: Alessio Michelassi
Author-email: alessio.michelassi@gmail.com
Classifier: Programming Language :: Python :: 3
Classifier: License :: OSI Approved :: MIT License
Classifier: Operating System :: OS Independent
Requires-Python: >=3.6
License-File: LICENSE.md
Requires-Dist: PyQt6
Dynamic: author
Dynamic: author-email
Dynamic: classifier
Dynamic: description
Dynamic: description-content-type
Dynamic: home-page
Dynamic: requires-dist
Dynamic: requires-python
Dynamic: summary
